paginate_sqlalchemy/__init__.py
paginate_sqlalchemy-0.3.1.dist-info/LICENSE
paginate_sqlalchemy-0.3.1.dist-info/METADATA
paginate_sqlalchemy-0.3.1.dist-info/WHEEL
paginate_sqlalchemy-0.3.1.dist-info/entry_points.txt
paginate_sqlalchemy-0.3.1.dist-info/top_level.txt
paginate_sqlalchemy-0.3.1.dist-info/RECORD
