Metadata-Version: 1.2
Name: paginate-sqlalchemy
Version: 0.3.1
Summary: Extension to paginate.Page that supports SQLAlchemy queries
Home-page: https://github.com/Pylons/paginate_sqlalchemy
Author: Christoph Haas
Author-email: email@christoph-haas.de
Maintainer: Luke Crooks
Maintainer-email: luke@pumalo.org
License: MIT
Keywords: pagination paginate sqlalchemy
Platform: UNKNOWN
Classifier: Programming Language :: Python
Classifier: Programming Language :: Python :: 2
Classifier: Programming Language :: Python :: 3
Classifier: Development Status :: 4 - Beta
Classifier: Intended Audience :: Developers
Classifier: License :: OSI Approved :: MIT License
Classifier: Topic :: Software Development :: Libraries :: Python Modules
